libtimer/__init__.py
libtimer-1.0.dist-info/METADATA
libtimer-1.0.dist-info/WHEEL
libtimer-1.0.dist-info/top_level.txt
libtimer-1.0.dist-info/RECORD
